mathematics_dataset/__init__.py
mathematics_dataset/example.py
mathematics_dataset/generate.py
mathematics_dataset/generate_settings.py
mathematics_dataset/generate_test.py
mathematics_dataset/generate_to_file.py
mathematics_dataset/modules/__init__.py
mathematics_dataset/modules/algebra.py
mathematics_dataset/modules/algebra_test.py
mathematics_dataset/modules/arithmetic.py
mathematics_dataset/modules/arithmetic_test.py
mathematics_dataset/modules/calculus.py
mathematics_dataset/modules/calculus_test.py
mathematics_dataset/modules/comparison.py
mathematics_dataset/modules/measurement.py
mathematics_dataset/modules/modules.py
mathematics_dataset/modules/numbers.py
mathematics_dataset/modules/polynomials.py
mathematics_dataset/modules/probability.py
mathematics_dataset/modules/train_test_split.py
mathematics_dataset/sample/__init__.py
mathematics_dataset/sample/arithmetic.py
mathematics_dataset/sample/arithmetic_test.py
mathematics_dataset/sample/linear_system.py
mathematics_dataset/sample/linear_system_test.py
mathematics_dataset/sample/number.py
mathematics_dataset/sample/number_test.py
mathematics_dataset/sample/ops.py
mathematics_dataset/sample/ops_test.py
mathematics_dataset/sample/polynomials.py
mathematics_dataset/sample/polynomials_test.py
mathematics_dataset/util/__init__.py
mathematics_dataset/util/combinatorics.py
mathematics_dataset/util/combinatorics_test.py
mathematics_dataset/util/composition.py
mathematics_dataset/util/composition_test.py
mathematics_dataset/util/display.py
mathematics_dataset/util/display_test.py
mathematics_dataset/util/probability.py
mathematics_dataset/util/probability_test.py
mathematics_dataset-1.0.dist-info/LICENSE
mathematics_dataset-1.0.dist-info/METADATA
mathematics_dataset-1.0.dist-info/WHEEL
mathematics_dataset-1.0.dist-info/top_level.txt
mathematics_dataset-1.0.dist-info/RECORD
